{"cameraMode":{"drawMode":2,"name":"Shaded Wireframe","section":"Shading Mode"},"sceneLighting":false,"audioPlay":false,"sceneViewState":{"m_AlwaysRefresh":false,"showFog":true,"showSkybox":true,"showFlares":true,"showImageEffects":true,"showParticleSystems":true,"showVisualEffectGraphs":true,"m_FxEnabled":true},"in2DMode":false,"pivot":{"x":2.466296672821045,"y":-1.1231696605682374,"z":5.765100479125977},"rotation":{"x":-0.11276550590991974,"y":-0.14935077726840974,"z":0.0171461571007967,"w":-0.9821895360946655},"size":5.139163017272949,"orthographic":false}